ocp_freecad_cam/__init__.py
ocp_freecad_cam/api.py
ocp_freecad_cam/api_tool.py
ocp_freecad_cam/api_util.py
ocp_freecad_cam/common.py
ocp_freecad_cam/fc_impl.py
ocp_freecad_cam/fc_impl_util.py
ocp_freecad_cam/visualizer.py
ocp_freecad_cam-1.1.0.dist-info/licenses/LICENSE
ocp_freecad_cam-1.1.0.dist-info/METADATA
ocp_freecad_cam-1.1.0.dist-info/WHEEL
ocp_freecad_cam-1.1.0.dist-info/top_level.txt
ocp_freecad_cam-1.1.0.dist-info/RECORD
